pytreefind/__init__.py
pytreefind/tree.py
pytreefind-0.1.1.dist-info/LICENSE
pytreefind-0.1.1.dist-info/METADATA
pytreefind-0.1.1.dist-info/WHEEL
pytreefind-0.1.1.dist-info/entry_points.txt
pytreefind-0.1.1.dist-info/RECORD
